README.md
setup.cfg
setup.py
ervin/__init__.py
ervin/__main__.py
ervin/defaults.py
ervin/ervin.py
ervin/ervin_utils.py
ervin/exceptions.py
ervin/probe_blaster.py
ervin/probe_data.py
ervin/probe_finder.py
ervin/scaf_file.py
ervin/scaf_to_fasta.py
ervin/sequence_expander.py
ervin/sequence_hunter.py
ervin/virus_blaster.py
ervin.egg-info/PKG-INFO
ervin.egg-info/SOURCES.txt
ervin.egg-info/dependency_links.txt
ervin.egg-info/entry_points.txt
ervin.egg-info/requires.txt
ervin.egg-info/top_level.txt
ervin/templates/__init__.py
ervin/templates/config_template.py