Metadata-Version: 2.1
Name: ervin
Version: 0.0.6
Summary: ERVin is a collection of tools developed to assist in discovering ERV sequences within genomic data
Home-page: https://github.com/strongles/ervin
Author: Rob Williams
Author-email: robccwilliams@gmail.com
License: GPL-3.0-or-later
Download-URL: https://github.com/strongles/ervin/archive/0.0.6.tar.gz
Platform: UNKNOWN
Classifier: Development Status :: 3 - Alpha
Classifier: License :: OSI Approved :: GNU General Public License v3 or later (GPLv3+)
Classifier: Programming Language :: Python :: 3.6
Classifier: Programming Language :: Python :: 3.7
Classifier: Environment :: MacOS X
Classifier: Intended Audience :: Science/Research
Classifier: Operating System :: MacOS :: MacOS X
Classifier: Topic :: Scientific/Engineering :: Bio-Informatics
